{"inkVersion":21,"root":[[{"->":"Outro"},["done",{"#f":5,"#n":"g-0"}],null],"done",{"Trigger":[{"temp=":"name"},{"#f":1}],"StartChallenge":[{"temp=":"name"},{"#f":1}],"Outro":[["ev","str","^name","/str",{"x()":"Trigger","exArgs":1},"pop","/ev","\n","^Tiens, t’es pas encore parti ?","#","^Bulle:NimuHautDroite","/#","\n","^Mes cheveux.","#","^Bulle:MorganHautDroite","/#","\n","ev","str","^name","/str",{"x()":"Trigger","exArgs":1},"pop","/ev","\n","^Ils étaient sur ta tête,<br> la dernière fois que j'ai checké.","#","^Bulle:NimuHautGauche","/#","\n","^Ils sont assez cool comme ça ?","#","^Bulle:MorganHautDroite","/#","\n","ev","str","^name","/str",{"x()":"Trigger","exArgs":1},"pop","/ev","\n","^Sur ta tête ?","#","^Bulle:NimuHautGauche","/#","\n","ev","str","^name","/str",{"x()":"Trigger","exArgs":1},"pop","/ev","\n","^Tu te retournes partiellement vers elle et fais ta fameuse \"moue inexpressive et sincèrement ennuyée\" jusqu'à ce qu'elle concède d'arrêter ses bêtises. ","#","^Bulle:Narrateur","/#","\n","^Ils sont parfaits tes 'veuch'.","#","^Bulle:NimuHautDroite","/#","\n","^Ok.<br>Et j’ai pas de taches de confiture dans le dos ?","#","^Bulle:MorganBasGauche","/#","\n","ev","str","^name","/str",{"x()":"Trigger","exArgs":1},"pop","/ev","\n","^Tu te contortionnes de nouveau pour lui faire observer ta chemise.","#","^Bulle:Narrateur","/#","\n","^Mais<bounce>…</bounce> pourquoi t’aurais<br> de la confiture dans le<bounce>…</bounce><br> <shake>Non<shake> ! ","#","^Bulle:NimuHautDroite","/#","\n","^Tu pousses un soupir de soulagement et te frottes les mains un instant.","#","^Bulle:Narrateur","/#","\n","^’kay. Brillant.","#","^Bulle:MorganHautDroite","/#","\n","ev","str","^name","/str",{"x()":"Trigger","exArgs":1},"pop","/ev","\n","^Prêt à partir, tu tapes successivement tes poches pour t'assurer que tout est bien à sa place <i>(pour la 21ème fois)</i>.","#","^Bulle:Narrateur","/#","\n","^Tu fronces les sourcils.","#","^Bulle:Narrateur","/#","\n","ev","str","^name","/str",{"x()":"Trigger","exArgs":1},"pop","/ev","\n","^T’aurais pas vu mes <wave>clefs</wave> ?","#","^Bulle:MorganHautauche","/#","\n","ev","str","^name","/str",{"x()":"Trigger","exArgs":1},"pop","/ev","\n","^Mais, tu vas décamper à la fin ?","#","^Bule:NimuHautDroite ","/#","#","^emot:!","/#","\n",["^Non, mais sincèrement !","#","^Bulle:MorganHautDroite","/#","\n","ev","str","^name","/str",{"x()":"Trigger","exArgs":1},"pop","/ev","\n","^J'mets pas la main d'ssus ! ","#","^Bulle:MorganHautGauche","/#","\n","^Ta grand-mère te considère un instant, les poings sur les hanches, avant de se mettre en mouvement. ","#","^Bulle:Narrateur","/#","\n","^Je vais t'prêter les miennes, t'inquiète.","#","^Bulle:NimuHautGauche","/#","\n","^Fluidement, elle s'approche du petit bol dans lequel elle laisse toujours ses clefs.","#","^Bulle:Narrateur","/#","\n","ev","str","^name","/str",{"x()":"Trigger","exArgs":1},"pop","/ev","\n","^Eeeh, galère.","#","^Bulle:NimuHautDroite","/#","\n","^<bounce>…</bounce> ","#","^Bulle:NimuHautDroite","/#","\n","^Je les retrouve pas non plus.","#","^Bulle:NimuHautDroite","/#","\n","ev","str","^name","/str",{"x()":"Trigger","exArgs":1},"pop","/ev","\n","^Ah. Cata. Pt'être dans l'canapé ? ","#","^Bulle:MorganBasGauche","/#","\n","ev","str","^S_Challenge","/str",{"x()":"StartChallenge","exArgs":1},"pop","/ev","\n","end",{"#f":5,"#n":"g-0"}],null],{"#f":1}],"#f":1}],"listDefs":{}}